util_demian/__init__.py
util_demian/utils.py
util_demian-0.0.4.dist-info/LICENSE
util_demian-0.0.4.dist-info/METADATA
util_demian-0.0.4.dist-info/WHEEL
util_demian-0.0.4.dist-info/top_level.txt
util_demian-0.0.4.dist-info/RECORD
