Metadata-Version: 2.1
Name: util-demian
Version: 0.0.4
Summary: utilities for demiansoft
Home-page: https://demiansoft.com/
Author: hyungjin kim
Author-email: hj3415@gmail.com
License: UNKNOWN
Project-URL: Bug Tracker, https://pypi.org/project/util-demian/
Platform: UNKNOWN
Classifier: License :: OSI Approved :: BSD License
Classifier: Operating System :: OS Independent
Classifier: Programming Language :: Python :: 3
Requires-Python: >=3.6
License-File: LICENSE
Requires-Dist: build (>=0.7.0)
